test/__init__.py
test/test_allanvar.py
test/test_calibration.py
tweezepy/MLE.py
tweezepy/__init__.py
tweezepy/allanvar.py
tweezepy/expressions.py
tweezepy/simulations.py
tweezepy/smmcalibration.py
Tweezepy-2021.6.13.dist-info/LICENSE
Tweezepy-2021.6.13.dist-info/METADATA
Tweezepy-2021.6.13.dist-info/WHEEL
Tweezepy-2021.6.13.dist-info/top_level.txt
Tweezepy-2021.6.13.dist-info/RECORD
