Metadata-Version: 2.1
Name: Tweezepy
Version: 2021.6.13
Summary: Single-molecule force spectroscopy calibration
Home-page: https://github.com/ianlmorgan/tweezepy
Author: Ian L. Morgan
Author-email: ilmorgan@ucsb.edu
License: LGPLv3+
Platform: UNKNOWN
License-File: LICENSE
Requires-Dist: numpy
Requires-Dist: scipy
Requires-Dist: autograd
Requires-Dist: emcee
